dm_aioaiagent/__init__.py
dm_aioaiagent/ai_agent.py
dm_aioaiagent/async_ai_agent.py
dm_aioaiagent/openai_image_message_content.py
dm_aioaiagent/types.py
dm_aioaiagent-0.5.7.dist-info/METADATA
dm_aioaiagent-0.5.7.dist-info/WHEEL
dm_aioaiagent-0.5.7.dist-info/top_level.txt
dm_aioaiagent-0.5.7.dist-info/RECORD
