Metadata-Version: 2.4
Name: dm-aioaiagent
Version: 0.5.7
Summary: This is my custom aioaiagent client
Home-page: https://pypi.org/project/dm-aioaiagent
Author: dimka4621
Author-email: mismartconfig@gmail.com
Project-URL: GitHub, https://github.com/MykhLibs/dm-aioaiagent
Keywords: dm aioaiagent
Classifier: Programming Language :: Python :: 3.9
Classifier: License :: OSI Approved :: MIT License
Classifier: Operating System :: OS Independent
Requires-Python: >=3.9
Requires-Dist: dm-logger<0.7.0,>=0.6.6
Requires-Dist: python-dotenv>=1.0.0
Requires-Dist: pydantic<3.0.0,>=2.9.2
Requires-Dist: langchain<0.4.0,>=0.3.0
Requires-Dist: langchain-core<0.4.0,>=0.3.5
Requires-Dist: langchain-community<0.4.0,>=0.3.0
Requires-Dist: langchain-openai<0.4.0,>=0.3.0
Requires-Dist: langchain-anthropic<0.4.0,>=0.3.0
Requires-Dist: langgraph<0.4.0,>=0.3.23
Requires-Dist: langsmith<0.4.0,>=0.3.45
Requires-Dist: grandalf<0.9.0,>=0.8.0
Dynamic: author
Dynamic: author-email
Dynamic: classifier
Dynamic: description
Dynamic: description-content-type
Dynamic: home-page
Dynamic: keywords
Dynamic: project-url
Dynamic: requires-dist
Dynamic: requires-python
Dynamic: summary
